chattingtransformer/__init__.py
chattingtransformer/chatting_transformer.py
chattingtransformer/settings.py
chattingtransformer-1.0.3.dist-info/LICENSE
chattingtransformer-1.0.3.dist-info/METADATA
chattingtransformer-1.0.3.dist-info/WHEEL
chattingtransformer-1.0.3.dist-info/top_level.txt
chattingtransformer-1.0.3.dist-info/RECORD
