Metadata-Version: 2.1
Name: chattingtransformer
Version: 1.0.3
Summary: GPT2 text generation with just two lines of code!
Home-page: https://github.com/Vennify-Inc/chatting-transformer
Author: Vennify Inc
Author-email: eric@vennify.ca
License: Apache 2.0
Keywords: gpt2,artificial,intelligence,ai,text,generation,chatting,vennify,gpt,transformer,transformers,nlp,nlu,natural,language,processing,understanding
Platform: UNKNOWN
Classifier: Development Status :: 3 - Alpha
Classifier: Intended Audience :: Developers
Classifier: Intended Audience :: Science/Research
Classifier: License :: OSI Approved :: Apache Software License
Classifier: Programming Language :: Python :: 3.6
Classifier: Programming Language :: Python :: 3.7
Classifier: Topic :: Text Processing :: Linguistic
Classifier: Topic :: Scientific/Engineering :: Artificial Intelligence
Classifier: Natural Language :: English
Requires-Dist: transformers (>=3.1.0)
Requires-Dist: torch (>=1.6.0)
